rustats-0.1.7.dist-info/METADATA
rustats-0.1.7.dist-info/WHEEL
rustats/__init__.py
rustats/rustats.cpython-312-aarch64-linux-gnu.so
rustats-0.1.7.dist-info/RECORD
